[1,["0coClSuNpGB6naKDcspkLU"],["_textureSetter"],["cc.SpriteFrame"],0,[[[{"name":"bt-how","rect":[880,35,110,61],"offset":[0,0],"originalSize":[110,61],"capInsets":[0,0,0,0]}],[0],0,[0],[0],[0]],[[{"name":"line2","rect":[1250,98,275,70],"offset":[0,0],"originalSize":[275,70],"capInsets":[0,0,0,0]}],[0],0,[0],[0],[0]],[[{"name":"bt-home","rect":[1208,35,109,63],"offset":[0,0],"originalSize":[109,63],"capInsets":[0,0,0,0]}],[0],0,[0],[0],[0]],[[{"name":"bt-setting","rect":[990,35,109,61],"offset":[0,0],"originalSize":[109,61],"capInsets":[0,0,0,0]}],[0],0,[0],[0],[0]]]]